[
  {
    "constant": true,
    "inputs": [
      {
        "components": [
          {
            "internalType": "string",
            "name": "description",
            "type": "string"
          },
          {
            "components": [
              {
                "internalType": "string",
                "name": "face",
                "type": "string"
              },
              {
                "internalType": "string",
                "name": "eyes",
                "type": "string"
              },
              {
                "internalType": "string",
                "name": "betweenEyes",
                "type": "string"
              },
              {
                "internalType": "string",
                "name": "mouth",
                "type": "string"
              },
              {
                "internalType": "string",
                "name": "body",
                "type": "string"
              }
            ],
            "internalType": "struct Avatars.Options",
            "name": "options",
            "type": "tuple"
          },
          {
            "components": [
              {
                "components": [
                  {
                    "internalType": "string",
                    "name": "key",
                    "type": "string"
                  },
                  {
                    "internalType": "string",
                    "name": "color",
                    "type": "string"
                  }
                ],
                "internalType": "struct Avatars.Item",
                "name": "face",
                "type": "tuple"
              },
              {
                "components": [
                  {
                    "internalType": "string",
                    "name": "key",
                    "type": "string"
                  },
                  {
                    "internalType": "string",
                    "name": "color",
                    "type": "string"
                  }
                ],
                "internalType": "struct Avatars.Item",
                "name": "hair",
                "type": "tuple"
              },
              {
                "components": [
                  {
                    "internalType": "string",
                    "name": "key",
                    "type": "string"
                  },
                  {
                    "internalType": "string",
                    "name": "color",
                    "type": "string"
                  }
                ],
                "internalType": "struct Avatars.Item",
                "name": "eyebrows",
                "type": "tuple"
              },
              {
                "components": [
                  {
                    "internalType": "string",
                    "name": "key",
                    "type": "string"
                  },
                  {
                    "internalType": "string",
                    "name": "color",
                    "type": "string"
                  }
                ],
                "internalType": "struct Avatars.Item",
                "name": "eyes",
                "type": "tuple"
              },
              {
                "components": [
                  {
                    "internalType": "string",
                    "name": "key",
                    "type": "string"
                  },
                  {
                    "internalType": "string",
                    "name": "color",
                    "type": "string"
                  }
                ],
                "internalType": "struct Avatars.Item",
                "name": "nose",
                "type": "tuple"
              },
              {
                "components": [
                  {
                    "internalType": "string",
                    "name": "key",
                    "type": "string"
                  },
                  {
                    "internalType": "string",
                    "name": "color",
                    "type": "string"
                  }
                ],
                "internalType": "struct Avatars.Item",
                "name": "mouth",
                "type": "tuple"
              },
              {
                "components": [
                  {
                    "internalType": "string",
                    "name": "key",
                    "type": "string"
                  },
                  {
                    "internalType": "string",
                    "name": "color",
                    "type": "string"
                  }
                ],
                "internalType": "struct Avatars.Item",
                "name": "clothes",
                "type": "tuple"
              },
              {
                "components": [
                  {
                    "internalType": "string",
                    "name": "key",
                    "type": "string"
                  },
                  {
                    "internalType": "string",
                    "name": "color",
                    "type": "string"
                  }
                ],
                "internalType": "struct Avatars.Item",
                "name": "body",
                "type": "tuple"
              },
              {
                "components": [
                  {
                    "internalType": "string",
                    "name": "key",
                    "type": "string"
                  },
                  {
                    "internalType": "string",
                    "name": "color",
                    "type": "string"
                  }
                ],
                "internalType": "struct Avatars.Item",
                "name": "background",
                "type": "tuple"
              },
              {
                "components": [
                  {
                    "internalType": "string",
                    "name": "key",
                    "type": "string"
                  },
                  {
                    "internalType": "string",
                    "name": "color",
                    "type": "string"
                  }
                ],
                "internalType": "struct Avatars.Item",
                "name": "outwear",
                "type": "tuple"
              },
              {
                "components": [
                  {
                    "internalType": "string",
                    "name": "key",
                    "type": "string"
                  },
                  {
                    "internalType": "string",
                    "name": "color",
                    "type": "string"
                  }
                ],
                "internalType": "struct Avatars.Item",
                "name": "hat",
                "type": "tuple"
              },
              {
                "components": [
                  {
                    "internalType": "string",
                    "name": "key",
                    "type": "string"
                  },
                  {
                    "internalType": "string",
                    "name": "color",
                    "type": "string"
                  }
                ],
                "internalType": "struct Avatars.Item",
                "name": "glasses",
                "type": "tuple"
              },
              {
                "components": [
                  {
                    "internalType": "string",
                    "name": "key",
                    "type": "string"
                  },
                  {
                    "internalType": "string",
                    "name": "color",
                    "type": "string"
                  }
                ],
                "internalType": "struct Avatars.Item",
                "name": "accessory",
                "type": "tuple"
              },
              {
                "components": [
                  {
                    "internalType": "string",
                    "name": "key",
                    "type": "string"
                  },
                  {
                    "internalType": "string",
                    "name": "color",
                    "type": "string"
                  }
                ],
                "internalType": "struct Avatars.Item",
                "name": "expression",
                "type": "tuple"
              },
              {
                "components": [
                  {
                    "internalType": "string",
                    "name": "key",
                    "type": "string"
                  },
                  {
                    "internalType": "string",
                    "name": "color",
                    "type": "string"
                  }
                ],
                "internalType": "struct Avatars.Item",
                "name": "hand",
                "type": "tuple"
              },
              {
                "components": [
                  {
                    "internalType": "string",
                    "name": "key",
                    "type": "string"
                  },
                  {
                    "internalType": "string",
                    "name": "color",
                    "type": "string"
                  }
                ],
                "internalType": "struct Avatars.Item",
                "name": "balloon",
                "type": "tuple"
              },
              {
                "components": [
                  {
                    "internalType": "string",
                    "name": "key",
                    "type": "string"
                  },
                  {
                    "internalType": "string",
                    "name": "color",
                    "type": "string"
                  }
                ],
                "internalType": "struct Avatars.Item",
                "name": "pet",
                "type": "tuple"
              },
              {
                "components": [
                  {
                    "internalType": "string",
                    "name": "key",
                    "type": "string"
                  },
                  {
                    "internalType": "string",
                    "name": "color",
                    "type": "string"
                  }
                ],
                "internalType": "struct Avatars.Item",
                "name": "goods",
                "type": "tuple"
              }
            ],
            "internalType": "struct Avatars.Items",
            "name": "items",
            "type": "tuple"
          }
        ],
        "internalType": "struct Avatars.Avatar",
        "name": "avatar",
        "type": "tuple"
      }
    ],
    "name": "isValid",
    "outputs": [
      {
        "internalType": "bool",
        "name": "",
        "type": "bool"
      }
    ],
    "payable": false,
    "stateMutability": "pure",
    "type": "function"
  }
]